MANIFEST.in
README.rst
setup.cfg
setup.py
docs/HISTORY.rst
docs/INSTALL.txt
docs/LICENSE.GPL
docs/LICENSE.txt
redturtle/__init__.py
redturtle.lookup.egg-info/PKG-INFO
redturtle.lookup.egg-info/SOURCES.txt
redturtle.lookup.egg-info/dependency_links.txt
redturtle.lookup.egg-info/entry_points.txt
redturtle.lookup.egg-info/namespace_packages.txt
redturtle.lookup.egg-info/not-zip-safe
redturtle.lookup.egg-info/requires.txt
redturtle.lookup.egg-info/top_level.txt
redturtle/lookup/__init__.py
redturtle/lookup/admin.py
redturtle/lookup/configure.zcml
redturtle/lookup/interfaces.py
redturtle/lookup/api/__init__.py
redturtle/lookup/api/configure.zcml
redturtle/lookup/api/view.py
redturtle/lookup/app/.editorconfig
redturtle/lookup/app/.eslintrc
redturtle/lookup/app/.flowconfig
redturtle/lookup/app/.gitignore
redturtle/lookup/app/.nvmrc
redturtle/lookup/app/.prettierrc.json
redturtle/lookup/app/package-lock.json
redturtle/lookup/app/package.json
redturtle/lookup/app/yarn.lock
redturtle/lookup/app/build/asset-manifest.json
redturtle/lookup/app/build/favicon.ico
redturtle/lookup/app/build/index.html
redturtle/lookup/app/build/manifest.json
redturtle/lookup/app/build/service-worker.js
redturtle/lookup/app/build/static/css/main.d159ad6e.css
redturtle/lookup/app/build/static/css/main.d159ad6e.css.map
redturtle/lookup/app/build/static/js/main.7250b3a2.js
redturtle/lookup/app/build/static/js/main.7250b3a2.js.map
redturtle/lookup/app/build/static/media/brand-icons.13db00b7.eot
redturtle/lookup/app/build/static/media/brand-icons.a046592b.woff
redturtle/lookup/app/build/static/media/brand-icons.a1a749e8.svg
redturtle/lookup/app/build/static/media/brand-icons.c5ebe0b3.ttf
redturtle/lookup/app/build/static/media/brand-icons.e8c322de.woff2
redturtle/lookup/app/build/static/media/flags.9c74e172.png
redturtle/lookup/app/build/static/media/icons.0ab54153.woff2
redturtle/lookup/app/build/static/media/icons.8e3c7f55.eot
redturtle/lookup/app/build/static/media/icons.962a1bf3.svg
redturtle/lookup/app/build/static/media/icons.b87b9ba5.ttf
redturtle/lookup/app/build/static/media/icons.faff9214.woff
redturtle/lookup/app/build/static/media/outline-icons.701ae6ab.eot
redturtle/lookup/app/build/static/media/outline-icons.82f60bd0.svg
redturtle/lookup/app/build/static/media/outline-icons.ad97afd3.ttf
