Metadata-Version: 2.1
Name: redturtle.lookup
Version: 3.1.0
Summary: List products information for different Plone sites in a single instance
Home-page: https://github.com/RedTurtle/redturtle.lookup
Author: RedTurtle
Author-email: sviluppoplone@redturtle.it
License: GPL
Keywords: Python Plone
Platform: UNKNOWN
Classifier: Environment :: Web Environment
Classifier: Framework :: Plone
Classifier: Framework :: Plone :: 5.0
Classifier: Framework :: Plone :: 5.1
Classifier: Programming Language :: Python
Classifier: Programming Language :: Python :: 2.7
Classifier: Operating System :: OS Independent
Classifier: License :: OSI Approved :: GNU General Public License v2 (GPLv2)
Provides-Extra: test
